Lab2/mux.v
// // output is A (when control == 0) or B (when control == 1)
// module mux2(out, A, B, control);
//     output out;
//     input  A, B;
//     input  control;
//     wire   wA, wB, not_control;
         
//     not n1(not_control, control);
//     and a1(wA, A, not_control);
//     and a2(wB, B, control);
//     or  o1(out, wA, wB);
// endmodule // mux2

// // output is A (when control == 00) or B (when control == 01) or
// //           C (when control == 10) or D (when control == 11)
// module mux4(out, A, B, C, D, control);
//     output      out;
//     input       A, B, C, D;
//     input [1:0] control;

// endmodule // mux4


// output is A (when control == 0) or B (when control == 1)
module mux2(out, A, B, control);
    output out;
    input  A, B;
    input  control;
    wire   wA, wB, not_control;

    not n1(not_control, control);
    and a1(wA, A, not_control);
    and a2(wB, B, control);
    or  o1(out, wA, wB);
endmodule // mux2

// output is A (when control == 00) or B (when control == 01) or
//           C (when control == 10) or D (when control == 11)
module mux4(out, A, B, C, D, control);
    output      out;
    input       A, B, C, D;
    input [1:0] control;
    wire m1, m2;

    mux2 mu1(m1, A, B, control[0]);
    mux2 mu2(m2, C, D, control[0]);
    mux2 mu3(out, m1, m2, control[1]);

endmodule // mux4

Lab2/logicunit.v
// 00 -> AND, 01 -> OR, 10 -> NOR, 11 -> XOR
module mux4v(out, A, B, C, D, control);
  output      out;
  input       A, B, C, D;
  input [1:0] control;

  wire  wA, wB, wC, wD;

  assign wA = A & (control == 2'b00);
  assign wB = B & (control == 2'b01);
  assign wC = C & (control == 2'b10);
  assign wD = D & (control == 2'b11);

  or  o1(out, wA, wB, wC, wD);

endmodule // mux4v

// Design a logicunit that implements the specified truth table
//00 -> AND, 01 -> OR, 10 -> NOR, 11 -> XOR

module logicunit(out, A, B, control);
  output      out;
  input       A, B;
  input [1:0] control;
  wire an, o, no, xo;

  and na1(an, A, B);
  or a1(o, A, B);
  nor o1(no, A, B);
  xor no1(xo, A, B);
  mux4v mux4(out, an, o, no, xo, control);

endmodule // Logic Unit to Verilog

Lab2/alu1.v
// module full_adder(sum, cout, a, b, cin);
//     output sum, cout;
//     input  a, b, cin;
//     wire   partial_s, partial_c1, partial_c2;

//     xor x0(partial_s, a, b);
//     xor x1(sum, partial_s, cin);
//     and a0(partial_c1, a, b);
//     and a1(partial_c2, partial_s, cin);
//     or  o1(cout, partial_c1, partial_c2);
// endmodule // full_adder

// `define ALU_ADD    3'h2
// `define ALU_SUB    3'h3
// `define ALU_AND    3'h4
// `define ALU_OR     3'h5
// `define ALU_NOR    3'h6
// `define ALU_XOR    3'h7

// // 01x -> arithmetic, 1xx -> logic
// module alu1(out, carryout, A, B, carryin, control);
//     output      out, carryout;
//     input       A, B, carryin;
//     input [2:0] control;

//     // add code here!!!

// endmodule // alu1

module full_adder(sum, cout, a, b, cin);
    output sum, cout;
    input  a, b, cin;
    wire   partial_s, partial_c1, partial_c2;

    xor x0(partial_s, a, b);
    xor x1(sum, partial_s, cin);
    and a0(partial_c1, a, b);
    and a1(partial_c2, partial_s, cin);
    or  o1(cout, partial_c1, partial_c2);
endmodule // full_adder

// define ALU_ADD    3'h2;
// define ALU_SUB    3'h3;
// define ALU_AND    3'h4;
// define ALU_OR     3'h5;
// define ALU_NOR    3'h6;
// define ALU_XOR    3'h7;

// 01x -> arithmetic, 1xx -> logic
module alu1(out, carryout, A, B, carryin, control);
    output      out, carryout;
    input       A, B, carryin;
    input [2:0] control;

    // add code here!!!
    wire BB;

    xor bxor(BB, B, control[0]);

    wire fa_sum, lu_out;
    full_adder fa(fa_sum, carryout, A, BB, carryin);
    logicunit lu(lu_out, A, B, control[1:0]);
    mux2 mux2v(out, fa_sum, lu_out, control[2]);

endmodule // alu1

Lab2/alu1_tb.v
module alu1_test;

    // define ALU_ADD    3'h2
    // define ALU_SUB    3'h3
    // define ALU_AND    3'h4
    // define ALU_OR     3'h5
    // define ALU_NOR    3'h6
    // define ALU_XOR    3'h7

    // cycle through all combinations of A, B, carryin every 16 time units
    reg A = 0;
    always #1 A = !A;
    reg B = 0;
    always #2 B = !B;
    reg carryin = 0;
    always #4 carryin = !carryin;

    reg [2:0] control = 0;

    initial begin
        $dumpfile("alu1.vcd");
        $dumpvars(0, alu1_test);

        // control is initially 0
        # 16 control = 010; // wait 16 time units (why 16?) and then set it to 1
        # 16 control = 011; // wait 16 time units and then set it to 2
        # 16 control = 100; // wait 16 time units and then set it to 3
        # 16 control = 101; // wait 16 time units and then set it to 4
        # 16 control = 110; // wait 16 time units and then set it to 5
        # 16 control = 111; // wait 16 time units and then set it to 6
        # 16 $finish; // wait 16 time units and then end the simulation
    end

    wire out;
    wire carryout;
    alu1 alu_1b(out, carryout, A, B, carryin, control);

    // you really should be using gtkwave instead
    /*
    initial begin
        $display("A B C D s o");
        $monitor("%d %d %d %d %d %d (at time %t)", A, B, C, D, control, out, $time);
    end
    */

endmodule

Lab2/alu1.vcd
$date
	Sun Sep  6 19:28:34 2020
$end
$version
	Icarus Verilog
$end
$timescale
	1s
$end
$scope module alu1_test $end
$var wire 1 ! out $end
$var wire 1 " carryout $end
$var reg 1 # A $end
$var reg 1 $ B $end
$var reg 1 % carryin $end
$var reg 3 & control [2:0] $end
$scope module alu_1b $end
$var wire 1 # A $end
$var wire 1 $ B $end
$var wire 1 ' BB $end
$var wire 1 % carryin $end
$var wire 3 ( control [2:0] $end
$var wire 1 ! out $end
$var wire 1 ) lu_out $end
$var wire 1 * fa_sum $end
$var wire 1 " carryout $end
$scope module fa $end
$var wire 1 # a $end
$var wire 1 ' b $end
$var wire 1 % cin $end
$var wire 1 " cout $end
$var wire 1 + partial_c1 $end
$var wire 1 , partial_c2 $end
$var wire 1 - partial_s $end
$var wire 1 * sum $end
$upscope $end
$scope module lu $end
$var wire 1 # A $end
$var wire 1 $ B $end
$var wire 1 . an $end
$var wire 2 / control [1:0] $end
$var wire 1 0 no $end
$var wire 1 1 o $end
$var wire 1 2 xo $end
$var wire 1 ) out $end
$scope module mux4 $end
$var wire 1 . A $end
$var wire 1 1 B $end
$var wire 1 0 C $end
$var wire 1 2 D $end
$var wire 2 3 control [1:0] $end
$var wire 1 ) out $end
$var wire 1 4 wA $end
$var wire 1 5 wB $end
$var wire 1 6 wC $end
$var wire 1 7 wD $end
$upscope $end
$upscope $end
$scope module mux2v $end
$var wire 1 * A $end
$var wire 1 ) B $end
$var wire 1 8 control $end
$var wire 1 9 not_control $end
$var wire 1 ! out $end
$var wire 1 : wA $end
$var wire 1 ; wB $end
$upscope $end
$upscope $end
$upscope $end
$enddefinitions $end
#0
$dumpvars
0;
0:
19
08
07
06
05
04
b0 3
02
01
10
b0 /
0.
0-
0,
0+
0*
0)
b0 (
0'
b0 &
0%
0$
0#
0"
0!
$end
#1
1!
1:
1*
1-
11
00
12
1#
#2
1'
0#
1$
#3
0!
0:
1)
0*
1"
14
0-
1+
1.
02
1#
#4
0)
1!
0"
04
1:
0+
0'
0.
01
10
1*
0#
0$
1%
#5
0!
0:
1"
0*
1,
1-
11
00
12
1#
#6
1'
0#
1$
#7
1!
1:
1)
1*
0,
14
0-
1+
1.
02
1#
#8
0)
0!
0"
04
0:
0+
0'
0.
01
10
0*
0#
0$
0%
#9
1!
1:
1*
1-
11
00
12
1#
#10
1'
0#
1$
#11
0!
0:
1)
0*
1"
14
0-
1+
1.
02
1#
#12
0)
1!
0"
04
1:
0+
0'
0.
01
10
1*
0#
0$
1%
#13
0!
0:
1"
0*
1,
1-
11
00
12
1#
#14
1'
0#
1$
#15
1!
1:
1)
1*
0,
14
0-
1+
1.
02
1#
#16
0!
0"
0:
04
16
0+
0'
0.
01
10
0*
b10 /
b10 3
0#
0$
0%
b10 &
b10 (
#17
1!
1:
0)
1*
06
1-
11
00
12
1#
#18
1'
0#
1$
#19
0!
0:
0*
1"
0-
1+
1.
02
1#
#20
1)
1!
0"
16
1:
0+
0'
0.
01
10
1*
0#
0$
1%
#21
0!
0:
1"
0)
0*
1,
06
1-
11
00
12
1#
#22
1'
0#
1$
#23
1!
1:
1*
0,
0-
1+
1.
02
1#
#24
1)
0!
0"
16
0:
0+
0'
0.
01
10
0*
0#
0$
0%
#25
1!
1:
0)
1*
06
1-
11
00
12
1#
#26
1'
0#
1$
#27
0!
0:
0*
1"
0-
1+
1.
02
1#
#28
1)
1!
0"
16
1:
0+
0'
0.
01
10
1*
0#
0$
1%
#29
0!
0:
1"
0)
0*
1,
06
1-
11
00
12
1#
#30
1'
0#
1$
#31
1!
1:
1*
0,
0-
1+
1.
02
1#
#32
1!
0"
1:
1-
0+
0.
01
10
1*
b11 /
b11 3
0#
0$
0%
b11 &
b11 (
#33
0!
0:
1)
0*
1"
17
0-
1+
11
00
12
1#
#34
0"
0+
0'
0#
1$
#35
1!
1:
0)
1*
07
1-
1.
02
1#
#36
0!
0:
1"
1'
0.
01
10
0*
1,
0#
0$
1%
#37
1!
1:
1)
1*
0,
17
0-
1+
11
00
12
1#
#38
0"
0+
0'
0#
1$
#39
0!
0:
1"
0)
0*
1,
07
1-
1.
02
1#
#40
1!
1:
0"
1'
0.
01
10
1*
0,
0#
0$
0%
#41
0!
0:
1)
0*
1"
17
0-
1+
11
00
12
1#
#42
0"
0+
0'
0#
1$
#43
1!
1:
0)
1*
07
1-
1.
02
1#
#44
0!
0:
1"
1'
0.
01
10
0*
1,
0#
0$
1%
#45
1!
1:
1)
1*
0,
17
0-
1+
11
00
12
1#
#46
0"
0+
0'
0#
1$
#47
0!
0:
1"
0)
0*
1,
07
1-
1.
02
1#
#48
0"
09
0-
0.
01
10
0*
0,
b0 /
b0 3
18
0#
0$
0%
b100 &
b100 (
#49
1*
1-
11
00
12
1#
#50
1'
0#
1$
#51
1!
1;
1)
0*
1"
14
0-
1+
1.
02
1#
#52
0!
0;
0)
0"
04
0+
0'
0.
01
10
1*
0#
0$
1%
#53
1"
0*
1,
1-
11
00
12
1#
#54
1'
0#
1$
#55
1!
1;
1)
1*
0,
14
0-
1+
1.
02
1#
#56
0!
0;
0)
0"
04
0+
0'
0.
01
10
0*
0#
0$
0%
#57
1*
1-
11
00
12
1#
#58
1'
0#
1$
#59
1!
1;
1)
0*
1"
14
0-
1+
1.
02
1#
#60
0!
0;
0)
0"
04
0+
0'
0.
01
10
1*
0#
0$
1%
#61
1"
0*
1,
1-
11
00
12
1#
#62
1'
0#
1$
#63
1!
1;
1)
1*
0,
14
0-
1+
1.
02
1#
#64
0!
0;
0)
0"
04
1-
0+
0.
01
10
1*
b1 /
b1 3
0#
0$
0%
b101 &
b101 (
#65
1!
1;
1)
0*
1"
15
0-
1+
11
00
12
1#
#66
0"
0+
0'
0#
1$
#67
1*
1-
1.
02
1#
#68
0!
0;
0)
05
1"
1'
0.
01
10
0*
1,
0#
0$
1%
#69
1!
1;
1)
1*
0,
15
0-
1+
11
00
12
1#
#70
0"
0+
0'
0#
1$
#71
1"
0*
1,
1-
1.
02
1#
#72
0!
0;
0)
05
0"
1'
0.
01
10
1*
0,
0#
0$
0%
#73
1!
1;
1)
0*
1"
15
0-
1+
11
00
12
1#
#74
0"
0+
0'
0#
1$
#75
1*
1-
1.
02
1#
#76
0!
0;
0)
05
1"
1'
0.
01
10
0*
1,
0#
0$
1%
#77
1!
1;
1)
1*
0,
15
0-
1+
11
00
12
1#
#78
0"
0+
0'
0#
1$
#79
1"
0*
1,
1-
1.
02
1#
#80
0"
05
16
0-
0.
01
10
0*
0,
b10 /
b10 3
0#
0$
0%
b110 &
b110 (
#81
0!
0;
0)
1*
06
1-
11
00
12
1#
#82
1'
0#
1$
#83
0*
1"
0-
1+
1.
02
1#
#84
1!
1;
1)
0"
16
0+
0'
0.
01
10
1*
0#
0$
1%
#85
0!
0;
1"
0)
0*
1,
06
1-
11
00
12
1#
#86
1'
0#
1$
#87
1*
0,
0-
1+
1.
02
1#
#88
1!
1;
1)
0"
16
0+
0'
0.
01
10
0*
0#
0$
0%
#89
0!
0;
0)
1*
06
1-
11
00
12
1#
#90
1'
0#
1$
#91
0*
1"
0-
1+
1.
02
1#
#92
1!
1;
1)
0"
16
0+
0'
0.
01
10
1*
0#
0$
1%
#93
0!
0;
1"
0)
0*
1,
06
1-
11
00
12
1#
#94
1'
0#
1$
#95
1*
0,
0-
1+
1.
02
1#
#96
0"
1-
0+
0.
01
10
1*
b11 /
b11 3
0#
0$
0%
b111 &
b111 (
#97
1!
1;
1)
0*
1"
17
0-
1+
11
00
12
1#
#98
0"
0+
0'
0#
1$
#99
0!
0;
0)
1*
07
1-
1.
02
1#
#100
1"
1'
0.
01
10
0*
1,
0#
0$
1%
#101
1!
1;
1)
1*
0,
17
0-
1+
11
00
12
1#
#102
0"
0+
0'
0#
1$
#103
0!
0;
1"
0)
0*
1,
07
1-
1.
02
1#
#104
0"
1'
0.
01
10
1*
0,
0#
0$
0%
#105
1!
1;
1)
0*
1"
17
0-
1+
11
00
12
1#
#106
0"
0+
0'
0#
1$
#107
0!
0;
0)
1*
07
1-
1.
02
1#
#108
1"
1'
0.
01
10
0*
1,
0#
0$
1%
#109
1!
1;
1)
1*
0,
17
0-
1+
11
00
12
1#
#110
0"
0+
0'
0#
1$
#111
0!
0;
1"
0)
0*
1,
07
1-
1.
02
1#
#112
0"
1'
0.
01
10
1*
0,
0#
0$
0%
